hanoi/__init__.py
hanoi/cli.py
hanoi/game/__init__.py
hanoi/game/colors.py
hanoi/game/constants.py
hanoi/game/exceptions.py
hanoi/game/game.py
hanoi/game/start_screen.py
hanoi/solver.py
hanoi_viz-0.3.8.dist-info/WHEEL
hanoi_viz-0.3.8.dist-info/entry_points.txt
hanoi_viz-0.3.8.dist-info/METADATA
hanoi_viz-0.3.8.dist-info/RECORD
