Metadata-Version: 2.3
Name: hanoi-viz
Version: 0.3.8
Summary: Visualize solving the tower of Hanoi problem
Keywords: recursion,algorithms,learning,simulation
Author: Eytan Ohana
License: MIT
Classifier: Programming Language :: Python
Classifier: Programming Language :: Python :: 3
Classifier: Programming Language :: Python :: 3 :: Only
Classifier: Programming Language :: Python :: 3.8
Classifier: Programming Language :: Python :: 3.9
Classifier: Programming Language :: Python :: 3.10
Classifier: Programming Language :: Python :: 3.11
Classifier: Programming Language :: Python :: 3.12
Classifier: Programming Language :: Python :: 3.13
Classifier: Intended Audience :: Developers
Classifier: License :: OSI Approved :: MIT License
Classifier: Topic :: Software Development :: Libraries
Classifier: Topic :: Education
Requires-Dist: pygame>=2.6.1
Requires-Dist: rich>=14.2.0
Requires-Python: >=3.8, <3.14
Project-URL: Homepage, https://github.com/eytanohana/Hanoi
Project-URL: Issues, https://github.com/eytanohana/Hanoi/issues
Project-URL: Repository, https://github.com/eytanohana/Hanoi
